mccode_plumber/__init__.py
mccode_plumber/conductor.py
mccode_plumber/epics.py
mccode_plumber/epics_watcher.py
mccode_plumber/forwarder.py
mccode_plumber/kafka.py
mccode_plumber/mccode.py
mccode_plumber/splitrun.py
mccode_plumber/utils.py
mccode_plumber/writer.py
mccode_plumber/file_writer_control/CommandChannel.py
mccode_plumber/file_writer_control/CommandHandler.py
mccode_plumber/file_writer_control/CommandStatus.py
mccode_plumber/file_writer_control/InThreadStatusTracker.py
mccode_plumber/file_writer_control/JobHandler.py
mccode_plumber/file_writer_control/JobStatus.py
mccode_plumber/file_writer_control/KafkaTopicUrl.py
mccode_plumber/file_writer_control/StateExtractor.py
mccode_plumber/file_writer_control/WorkerFinder.py
mccode_plumber/file_writer_control/WorkerJobPool.py
mccode_plumber/file_writer_control/WorkerStatus.py
mccode_plumber/file_writer_control/WriteJob.py
mccode_plumber/file_writer_control/__init__.py
mccode_plumber/manage/__init__.py
mccode_plumber/manage/efu.py
mccode_plumber/manage/ensure.py
mccode_plumber/manage/epics.py
mccode_plumber/manage/forwarder.py
mccode_plumber/manage/manager.py
mccode_plumber/manage/orchestrate.py
mccode_plumber/manage/triage_demo.py
mccode_plumber/manage/writer.py
mccode_plumber-0.17.1.dist-info/METADATA
mccode_plumber-0.17.1.dist-info/WHEEL
mccode_plumber-0.17.1.dist-info/entry_points.txt
mccode_plumber-0.17.1.dist-info/top_level.txt
mccode_plumber-0.17.1.dist-info/RECORD
