Metadata-Version: 2.4
Name: mccode-plumber
Version: 0.17.1
Author-email: Gregory Tucker <gregory.tucker@ess.eu>
Classifier: License :: OSI Approved :: BSD License
Classifier: Programming Language :: Python :: 3
Classifier: Programming Language :: Python :: 3 :: Only
Classifier: Programming Language :: Python :: 3.11
Classifier: Programming Language :: Python :: 3.12
Classifier: Programming Language :: Python :: 3.13
Requires-Dist: p4p
Requires-Dist: kafka-python>=2.2.11
Requires-Dist: ess-streaming-data-types>=0.14.0
Requires-Dist: restage>=0.10.1
Requires-Dist: mccode-to-kafka>=0.5.0
Requires-Dist: moreniius>=0.7.0
Requires-Dist: icecream
Requires-Dist: ephemeral-port-reserve
Provides-Extra: test
Requires-Dist: pytest; extra == "test"
Requires-Dist: niess>=0.1.4; extra == "test"
